EyesOnIt/__init__.py
EyesOnIt/eoi_add_stream_inputs.py
EyesOnIt/eoi_monitor_stream_inputs.py
EyesOnIt/eoi_process_image_inputs.py
EyesOnIt/eoi_response.py
EyesOnIt/eoi_stream_url_input.py
EyesOnIt/eoi_utils.py
EyesOnIt/sdk.py
EyesOnIt/elements/__init__.py
EyesOnIt/elements/eoi_alerting.py
EyesOnIt/elements/eoi_bounding_box.py
EyesOnIt/elements/eoi_genetec_alerting.py
EyesOnIt/elements/eoi_motion_detection.py
EyesOnIt/elements/eoi_object_description.py
EyesOnIt/elements/eoi_region.py
EyesOnIt-2.0.4.dist-info/LICENSE.txt
EyesOnIt-2.0.4.dist-info/METADATA
EyesOnIt-2.0.4.dist-info/WHEEL
EyesOnIt-2.0.4.dist-info/top_level.txt
EyesOnIt-2.0.4.dist-info/RECORD
