Metadata-Version: 2.1
Name: EyesOnIt
Version: 2.0.4
Summary: Advanced Large Vision Model computer vision supporting usage through no-code UI, SDK and REST interfaces.
Home-page: https://github.com/EyesOnIt-AI/EyesOnIt-python-sdk
Author: EyesOnIt
Author-email: EyesOnIt <support@eyesonit.us>
License: MIT
Requires-Python: >=3.8
License-File: LICENSE.txt
Requires-Dist: pydantic
Requires-Dist: Pillow
Requires-Dist: requests
